kgcnn/__init__.py
kgcnn/backend/__init__.py
kgcnn/backend/_jax.py
kgcnn/backend/_numpy.py
kgcnn/backend/_tensorflow.py
kgcnn/backend/_torch.py
kgcnn/crystal/__init__.py
kgcnn/crystal/base.py
kgcnn/crystal/graph_builder.py
kgcnn/crystal/preprocessor.py
kgcnn/crystal/periodic_table/__init__.py
kgcnn/crystal/periodic_table/periodic_table.csv
kgcnn/crystal/periodic_table/periodic_table.py
kgcnn/data/__init__.py
kgcnn/data/base.py
kgcnn/data/crystal.py
kgcnn/data/download.py
kgcnn/data/force.py
kgcnn/data/moleculenet.py
kgcnn/data/qm.py
kgcnn/data/serial.py
kgcnn/data/tudataset.py
kgcnn/data/utils.py
kgcnn/data/datasets/ClinToxDataset.py
kgcnn/data/datasets/CoraDataset.py
kgcnn/data/datasets/CoraLuDataset.py
kgcnn/data/datasets/ESOLDataset.py
kgcnn/data/datasets/FreeSolvDataset.py
kgcnn/data/datasets/GraphTUDataset2020.py
kgcnn/data/datasets/ISO17Dataset.py
kgcnn/data/datasets/LipopDataset.py
kgcnn/data/datasets/MD17Dataset.py
kgcnn/data/datasets/MD17RevisedDataset.py
kgcnn/data/datasets/MUTAGDataset.py
kgcnn/data/datasets/MatBenchDataset2020.py
kgcnn/data/datasets/MatProjectDielectricDataset.py
kgcnn/data/datasets/MatProjectEFormDataset.py
kgcnn/data/datasets/MatProjectGapDataset.py
kgcnn/data/datasets/MatProjectIsMetalDataset.py
kgcnn/data/datasets/MatProjectJdft2dDataset.py
kgcnn/data/datasets/MatProjectLogGVRHDataset.py
kgcnn/data/datasets/MatProjectLogKVRHDataset.py
kgcnn/data/datasets/MatProjectPerovskitesDataset.py
kgcnn/data/datasets/MatProjectPhononsDataset.py
kgcnn/data/datasets/MoleculeNetDataset2018.py
kgcnn/data/datasets/MutagenicityDataset.py
kgcnn/data/datasets/PROTEINSDataset.py
kgcnn/data/datasets/QM7Dataset.py
kgcnn/data/datasets/QM7bDataset.py
kgcnn/data/datasets/QM8Dataset.py
kgcnn/data/datasets/QM9Dataset.py
kgcnn/data/datasets/QM9MolNetDataset.py
kgcnn/data/datasets/SIDERDataset.py
kgcnn/data/datasets/Tox21MolNetDataset.py
kgcnn/data/datasets/__init__.py
kgcnn/data/transform/__init__.py
kgcnn/data/transform/base.py
kgcnn-4.0.2.dist-info/AUTHORS
kgcnn-4.0.2.dist-info/LICENSE
kgcnn-4.0.2.dist-info/METADATA
kgcnn-4.0.2.dist-info/WHEEL
kgcnn-4.0.2.dist-info/top_level.txt
kgcnn-4.0.2.dist-info/RECORD
