Metadata-Version: 2.1
Name: kgcnn
Version: 4.0.2
Summary: General Base Layers for Graph Convolutions with Keras
Home-page: https://github.com/aimat-lab/gcnn_keras
Author: Patrick Reiser
Author-email: patrick.reiser@kit.edu
Keywords: materials,science,machine,learning,deep,graph,networks,neural
Classifier: Programming Language :: Python :: 3
Classifier: Operating System :: OS Independent
Classifier: Intended Audience :: Science/Research
Classifier: Topic :: Scientific/Engineering :: Information Analysis
Classifier: Topic :: Scientific/Engineering :: Physics
Classifier: Topic :: Scientific/Engineering :: Chemistry
Classifier: Topic :: Software Development :: Libraries :: Python Modules
License-File: LICENSE
License-File: AUTHORS
Requires-Dist: keras (>=3.0.2)
Requires-Dist: numpy (>=1.23.0)
Requires-Dist: scikit-learn (>=1.1.3)
Requires-Dist: pandas (>=1.5.2)
Requires-Dist: scipy (>=1.9.3)
Requires-Dist: matplotlib (>=3.6.0)
Requires-Dist: rdkit (>=2022.9.2)
Requires-Dist: pymatgen (>=2022.11.7)
Requires-Dist: keras-tuner (>=1.1.3)
Requires-Dist: requests (>=2.28.1)
Requires-Dist: networkx (>=2.8.8)
Requires-Dist: sympy (>=1.11.1)
Requires-Dist: pyyaml (>=6.0)
Requires-Dist: ase (>=3.22.1)
Requires-Dist: click (>=7.1.2)
Requires-Dist: brotli (>=1.0.9)
Requires-Dist: h5py (>=3.9.0)
Requires-Dist: pyxtal (>=0.6.4)
Provides-Extra: openbabel
Requires-Dist: openbabel ; extra == 'openbabel'
